LICENSE
MANIFEST.in
README.md
setup.py
gumtool/__init__.py
gumtool/cli.py
gumtool/commands.py
gumtool.egg-info/PKG-INFO
gumtool.egg-info/SOURCES.txt
gumtool.egg-info/dependency_links.txt
gumtool.egg-info/entry_points.txt
gumtool.egg-info/not-zip-safe
gumtool.egg-info/requires.txt
gumtool.egg-info/top_level.txt