Metadata-Version: 1.1
Name: gumtool
Version: 0.0.4
Summary: A simple collection of tools that make running Gnome (3.10+) Ubuntu (14.04+) a little easier, especially on high-dpi hardware like the Retina MacbookPro.
Home-page: blog.thatjoseguy.com
Author: Jose A. Idar
Author-email: jose.idar@gmail.com
License: Apache License
